<?xml version="1.0" encoding="UTF-8"?>

<weather type="town" value="Peace River, AB">
  <months>
    <month month="1" precipitation="23">
      <temp min="-21" max="-9" />
      <wind min="Calm" max="Near_Gale" />
    </month>
    <month month="2" precipitation="16">
      <temp min="-18" max="-5" />
      <wind min="Calm" max="Near_Gale" />
    </month>
    <month month="3" precipitation="14">
      <temp min="-12" max="1" />
      <wind min="Calm" max="Near_Gale" />
    </month>
    <month month="4" precipitation="19">
      <temp min="-3" max="11" />
      <wind min="Calm" max="Near_Gale" />
    </month>
    <month month="5" precipitation="44">
      <temp min="2" max="18" />
      <wind min="Calm" max="Near_Gale" />
    </month>
    <month month="6" precipitation="65">
      <temp min="7" max="22" />
      <wind min="Calm" max="Near_Gale" />
    </month>
    <month month="7" precipitation="66">
      <temp min="9" max="24" />
      <wind min="Calm" max="Near_Gale" />
    </month>
    <month month="8" precipitation="46">
      <temp min="8" max="23" />
      <wind min="Calm" max="Near_Gale" />
    </month>
    <month month="9" precipitation="42">
      <temp min="3" max="18" />
      <wind min="Calm" max="Near_Gale" />
    </month>
    <month month="10" precipitation="23">
      <temp min="-3" max="10" />
      <wind min="Calm" max="Near_Gale" />
    </month>
    <month month="11" precipitation="25">
      <temp min="-12" max="-1" />
      <wind min="Calm" max="Near_Gale" />
    </month>
    <month month="12" precipitation="20">
      <temp min="-18" max="-7" />
      <wind min="Calm" max="Near_Gale" />
    </month>
  </months>
</weather>