<?xml version="1.0" encoding="UTF-8"?>
<airline>
<profile name="AeroMexico" iata="AM" color="Navy" country="157" CEO="Andres Labastida" mentality="Aggressive" market="Global" preferedairport="MEX">
  <narrative narrative="AeroMexico is the flag carrier of Mexico, based in Mexico City. It has been in operation since 1934 and is rapidly expanding, with destinations primarily in Mexico and North/Central America. Their fleet currently consists exclusively of Boeing aircraft, primarily the 737.  " />
</profile>
  <startdata>
      <routes>
          <route destination1="ACA" destination2="MEX" opened="2009" closed="2199"></route>
          <route destination1="ACA" destination2="TLC" opened="2009" closed="2199"></route>
          <route destination1="AGU" destination2="MEX" opened="2009" closed="2199"></route>
          <route destination1="ATL" destination2="CUN" opened="2009" closed="2199"></route>
          <route destination1="ATL" destination2="CZM" opened="2009" closed="2199"></route>
          <route destination1="ATL" destination2="GDL" opened="2009" closed="2199"></route>
          <route destination1="ATL" destination2="MEX" opened="2009" closed="2199"></route>
          <route destination1="ATL" destination2="MTY" opened="2009" closed="2199"></route>
          <route destination1="ATL" destination2="PVR" opened="2009" closed="2199"></route>
          <route destination1="ATL" destination2="SJD" opened="2009" closed="2199"></route>
          <route destination1="BJX" destination2="MEX" opened="2009" closed="2199"></route>
          <route destination1="BJX" destination2="MTY" opened="2009" closed="2199"></route>
          <route destination1="BJX" destination2="TIJ" opened="2009" closed="2199"></route>
          <route destination1="BNA" destination2="CUN" opened="2009" closed="2199"></route>
          <route destination1="BOG" destination2="MEX" opened="2009" closed="2199"></route>
          <route destination1="CCS" destination2="MEX" opened="2009" closed="2199"></route>
          <route destination1="CDG" destination2="MEX" opened="2009" closed="2199"></route>
          <route destination1="CEN" destination2="GDL" opened="2009" closed="2199"></route>
          <route destination1="CEN" destination2="HMO" opened="2009" closed="2199"></route>
          <route destination1="CEN" destination2="MEX" opened="2009" closed="2199"></route>
          <route destination1="CJS" destination2="CUU" opened="2009" closed="2199"></route>
          <route destination1="CJS" destination2="GDL" opened="2009" closed="2199"></route>
          <route destination1="CJS" destination2="HMO" opened="2009" closed="2199"></route>
          <route destination1="CJS" destination2="MEX" opened="2009" closed="2199"></route>
          <route destination1="CJS" destination2="MTY" opened="2009" closed="2199"></route>
          <route destination1="CJS" destination2="TIJ" opened="2009" closed="2199"></route>
          <route destination1="CME" destination2="MEX" opened="2009" closed="2199"></route>
          <route destination1="CPE" destination2="MEX" opened="2009" closed="2199"></route>
          <route destination1="CUL" destination2="GDL" opened="2009" closed="2199"></route>
          <route destination1="CUL" destination2="HMO" opened="2009" closed="2199"></route>
          <route destination1="CUL" destination2="LAP" opened="2009" closed="2199"></route>
          <route destination1="CUL" destination2="LTO" opened="2009" closed="2199"></route>
          <route destination1="CUL" destination2="MEX" opened="2009" closed="2199"></route>
          <route destination1="CUL" destination2="MTY" opened="2009" closed="2199"></route>
          <route destination1="CUN" destination2="ATL" opened="2009" closed="2199"></route>
          <route destination1="CUN" destination2="BNA" opened="2009" closed="2199"></route>
          <route destination1="CUN" destination2="CVG" opened="2009" closed="2199"></route>
          <route destination1="CUN" destination2="DFW" opened="2009" closed="2199"></route>
          <route destination1="CUN" destination2="DTW" opened="2009" closed="2199"></route>
          <route destination1="CUN" destination2="HAV" opened="2009" closed="2199"></route>
          <route destination1="CUN" destination2="IAH" opened="2009" closed="2199"></route>
          <route destination1="CUN" destination2="IND" opened="2009" closed="2199"></route>
          <route destination1="CUN" destination2="JFK" opened="2009" closed="2199"></route>
          <route destination1="CUN" destination2="LAX" opened="2009" closed="2199"></route>
          <route destination1="CUN" destination2="LIM" opened="2009" closed="2199"></route>
          <route destination1="CUN" destination2="MCO" opened="2009" closed="2199"></route>
          <route destination1="CUN" destination2="MEM" opened="2009" closed="2199"></route>
          <route destination1="CUN" destination2="MEX" opened="2009" closed="2199"></route>
          <route destination1="CUN" destination2="MTY" opened="2009" closed="2199"></route>
          <route destination1="CUN" destination2="PTY" opened="2009" closed="2199"></route>
          <route destination1="CUN" destination2="SLC" opened="2009" closed="2199"></route>
          <route destination1="CUN" destination2="TLC" opened="2009" closed="2199"></route>
          <route destination1="CUN" destination2="TPA" opened="2009" closed="2199"></route>
          <route destination1="CUU" destination2="CJS" opened="2009" closed="2199"></route>
          <route destination1="CUU" destination2="GDL" opened="2009" closed="2199"></route>
          <route destination1="CUU" destination2="HMO" opened="2009" closed="2199"></route>
          <route destination1="CUU" destination2="MEX" opened="2009" closed="2199"></route>
          <route destination1="CUU" destination2="MTY" opened="2009" closed="2199"></route>
          <route destination1="CUU" destination2="TRC" opened="2009" closed="2199"></route>
          <route destination1="CUZ" destination2="LIM" opened="2009" closed="2199"></route>
          <route destination1="CVG" destination2="CUN" opened="2009" closed="2199"></route>
          <route destination1="CZM" destination2="ATL" opened="2009" closed="2199"></route>
          <route destination1="DFW" destination2="CUN" opened="2009" closed="2199"></route>
          <route destination1="DFW" destination2="MEX" opened="2009" closed="2199"></route>
          <route destination1="DGO" destination2="MEX" opened="2009" closed="2199"></route>
          <route destination1="DGO" destination2="TIJ" opened="2009" closed="2199"></route>
          <route destination1="DTW" destination2="CUN" opened="2009" closed="2199"></route>
          <route destination1="DTW" destination2="MEX" opened="2009" closed="2199"></route>
          <route destination1="DTW" destination2="MTY" opened="2009" closed="2199"></route>
          <route destination1="EZE" destination2="MEX" opened="2009" closed="2199"></route>
          <route destination1="FAT" destination2="GDL" opened="2009" closed="2199"></route>
          <route destination1="GDL" destination2="ATL" opened="2009" closed="2199"></route>
          <route destination1="GDL" destination2="CEN" opened="2009" closed="2199"></route>
          <route destination1="GDL" destination2="CJS" opened="2009" closed="2199"></route>
          <route destination1="GDL" destination2="CUL" opened="2009" closed="2199"></route>
          <route destination1="GDL" destination2="CUU" opened="2009" closed="2199"></route>
          <route destination1="GDL" destination2="FAT" opened="2009" closed="2199"></route>
          <route destination1="GDL" destination2="HMO" opened="2009" closed="2199"></route>
          <route destination1="GDL" destination2="LAX" opened="2009" closed="2199"></route>
          <route destination1="GDL" destination2="MEX" opened="2009" closed="2199"></route>
          <route destination1="GDL" destination2="MTY" opened="2009" closed="2199"></route>
          <route destination1="GDL" destination2="MZT" opened="2009" closed="2199"></route>
          <route destination1="GDL" destination2="ONT" opened="2009" closed="2199"></route>
          <route destination1="GDL" destination2="ORD" opened="2009" closed="2199"></route>
          <route destination1="GDL" destination2="PTY" opened="2009" closed="2199"></route>
          <route destination1="GDL" destination2="PVR" opened="2009" closed="2199"></route>
          <route destination1="GDL" destination2="SJC" opened="2009" closed="2199"></route>
          <route destination1="GDL" destination2="SLC" opened="2009" closed="2199"></route>
          <route destination1="GDL" destination2="SMF" opened="2009" closed="2199"></route>
          <route destination1="GDL" destination2="TLC" opened="2009" closed="2199"></route>
          <route destination1="GDL" destination2="TRC" opened="2009" closed="2199"></route>
          <route destination1="GRU" destination2="LIM" opened="2009" closed="2199"></route>
          <route destination1="GRU" destination2="MEX" opened="2009" closed="2199"></route>
          <route destination1="GUA" destination2="MEX" opened="2009" closed="2199"></route>
          <route destination1="HAV" destination2="CUN" opened="2009" closed="2199"></route>
          <route destination1="HAV" destination2="MEX" opened="2009" closed="2199"></route>
          <route destination1="HMO" destination2="CEN" opened="2009" closed="2199"></route>
          <route destination1="HMO" destination2="CJS" opened="2009" closed="2199"></route>
          <route destination1="HMO" destination2="CUL" opened="2009" closed="2199"></route>
          <route destination1="HMO" destination2="CUU" opened="2009" closed="2199"></route>
          <route destination1="HMO" destination2="GDL" opened="2009" closed="2199"></route>
          <route destination1="HMO" destination2="LAX" opened="2009" closed="2199"></route>
          <route destination1="HMO" destination2="LMM" opened="2009" closed="2199"></route>
          <route destination1="HMO" destination2="MEX" opened="2009" closed="2199"></route>
          <route destination1="HMO" destination2="MTY" opened="2009" closed="2199"></route>
          <route destination1="HMO" destination2="MXL" opened="2009" closed="2199"></route>
          <route destination1="HMO" destination2="PHX" opened="2009" closed="2199"></route>
          <route destination1="HMO" destination2="PPE" opened="2009" closed="2199"></route>
          <route destination1="HMO" destination2="TIJ" opened="2009" closed="2199"></route>
          <route destination1="HUX" destination2="LAX" opened="2009" closed="2199"></route>
          <route destination1="HUX" destination2="MEX" opened="2009" closed="2199"></route>
          <route destination1="IAD" destination2="MEX" opened="2009" closed="2199"></route>
          <route destination1="IAH" destination2="CUN" opened="2009" closed="2199"></route>
          <route destination1="IAH" destination2="MEX" opened="2009" closed="2199"></route>
          <route destination1="IND" destination2="CUN" opened="2009" closed="2199"></route>
          <route destination1="JFK" destination2="CUN" opened="2009" closed="2199"></route>
          <route destination1="JFK" destination2="MEX" opened="2009" closed="2199"></route>
          <route destination1="JUL" destination2="CUZ" opened="2009" closed="2199"></route>
          <route destination1="LAP" destination2="CUL" opened="2009" closed="2199"></route>
          <route destination1="LAP" destination2="LAX" opened="2009" closed="2199"></route>
          <route destination1="LAP" destination2="MEX" opened="2009" closed="2199"></route>
          <route destination1="LAS" destination2="MEX" opened="2009" closed="2199"></route>
          <route destination1="LAS" destination2="MTY" opened="2009" closed="2199"></route>
          <route destination1="LAS" destination2="PPE" opened="2009" closed="2199"></route>
          <route destination1="LAX" destination2="CUN" opened="2009" closed="2199"></route>
          <route destination1="LAX" destination2="GDL" opened="2009" closed="2199"></route>
          <route destination1="LAX" destination2="HMO" opened="2009" closed="2199"></route>
          <route destination1="LAX" destination2="HUX" opened="2009" closed="2199"></route>
          <route destination1="LAX" destination2="LAP" opened="2009" closed="2199"></route>
          <route destination1="LAX" destination2="LTO" opened="2009" closed="2199"></route>
          <route destination1="LAX" destination2="MEX" opened="2009" closed="2199"></route>
          <route destination1="LAX" destination2="MZT" opened="2009" closed="2199"></route>
          <route destination1="LAX" destination2="PVR" opened="2009" closed="2199"></route>
          <route destination1="LAX" destination2="SJD" opened="2009" closed="2199"></route>
          <route destination1="LAX" destination2="ZIH" opened="2009" closed="2199"></route>
          <route destination1="LAX" destination2="ZLO" opened="2009" closed="2199"></route>
          <route destination1="LHR" destination2="MEX" opened="2009" closed="2199"></route>
          <route destination1="LIM" destination2="AQP" opened="2009" closed="2199"></route>
          <route destination1="LIM" destination2="CUN" opened="2009" closed="2199"></route>
          <route destination1="LIM" destination2="GRU" opened="2009" closed="2199"></route>
          <route destination1="LIM" destination2="MEX" opened="2009" closed="2199"></route>
          <route destination1="LMM" destination2="HMO" opened="2009" closed="2199"></route>
          <route destination1="LMM" destination2="MEX" opened="2009" closed="2199"></route>
          <route destination1="LMM" destination2="MZT" opened="2009" closed="2199"></route>
          <route destination1="LRD" destination2="MTY" opened="2009" closed="2199"></route>
          <route destination1="LTO" destination2="CUL" opened="2009" closed="2199"></route>
          <route destination1="LTO" destination2="LAX" opened="2009" closed="2199"></route>
          <route destination1="MAD" destination2="MEX" opened="2009" closed="2199"></route>
          <route destination1="MAM" destination2="MEX" opened="2009" closed="2199"></route>
          <route destination1="MCO" destination2="CUN" opened="2009" closed="2199"></route>
          <route destination1="MCO" destination2="MEX" opened="2009" closed="2199"></route>
          <route destination1="MEM" destination2="CUN" opened="2009" closed="2199"></route>
          <route destination1="MEX" destination2="ACA" opened="2009" closed="2199"></route>
          <route destination1="MEX" destination2="AGU" opened="2009" closed="2199"></route>
          <route destination1="MEX" destination2="ATL" opened="2009" closed="2199"></route>
          <route destination1="MEX" destination2="BJX" opened="2009" closed="2199"></route>
          <route destination1="MEX" destination2="BOG" opened="2009" closed="2199"></route>
          <route destination1="MEX" destination2="CCS" opened="2009" closed="2199"></route>
          <route destination1="MEX" destination2="CDG" opened="2009" closed="2199"></route>
          <route destination1="MEX" destination2="CEN" opened="2009" closed="2199"></route>
          <route destination1="MEX" destination2="CJS" opened="2009" closed="2199"></route>
          <route destination1="MEX" destination2="CME" opened="2009" closed="2199"></route>
          <route destination1="MEX" destination2="CPE" opened="2009" closed="2199"></route>
          <route destination1="MEX" destination2="CUL" opened="2009" closed="2199"></route>
          <route destination1="MEX" destination2="CUN" opened="2009" closed="2199"></route>
          <route destination1="MEX" destination2="CUU" opened="2009" closed="2199"></route>
          <route destination1="MEX" destination2="DFW" opened="2009" closed="2199"></route>
          <route destination1="MEX" destination2="DGO" opened="2009" closed="2199"></route>
          <route destination1="MEX" destination2="DTW" opened="2009" closed="2199"></route>
          <route destination1="MEX" destination2="EZE" opened="2009" closed="2199"></route>
          <route destination1="MEX" destination2="GDL" opened="2009" closed="2199"></route>
          <route destination1="MEX" destination2="GRU" opened="2009" closed="2199"></route>
          <route destination1="MEX" destination2="GUA" opened="2009" closed="2199"></route>
          <route destination1="MEX" destination2="HAV" opened="2009" closed="2199"></route>
          <route destination1="MEX" destination2="HMO" opened="2009" closed="2199"></route>
          <route destination1="MEX" destination2="HUX" opened="2009" closed="2199"></route>
          <route destination1="MEX" destination2="IAD" opened="2009" closed="2199"></route>
          <route destination1="MEX" destination2="IAH" opened="2009" closed="2199"></route>
          <route destination1="MEX" destination2="JFK" opened="2009" closed="2199"></route>
          <route destination1="MEX" destination2="LAP" opened="2009" closed="2199"></route>
          <route destination1="MEX" destination2="LAS" opened="2009" closed="2199"></route>
          <route destination1="MEX" destination2="LAX" opened="2009" closed="2199"></route>
          <route destination1="MEX" destination2="LHR" opened="2009" closed="2199"></route>
          <route destination1="MEX" destination2="LIM" opened="2009" closed="2199"></route>
          <route destination1="MEX" destination2="LMM" opened="2009" closed="2199"></route>
          <route destination1="MEX" destination2="MAD" opened="2009" closed="2199"></route>
          <route destination1="MEX" destination2="MAM" opened="2009" closed="2199"></route>
          <route destination1="MEX" destination2="MCO" opened="2009" closed="2199"></route>
          <route destination1="MEX" destination2="MIA" opened="2009" closed="2199"></route>
          <route destination1="MEX" destination2="MID" opened="2009" closed="2199"></route>
          <route destination1="MEX" destination2="MLM" opened="2009" closed="2199"></route>
          <route destination1="MEX" destination2="MTT" opened="2009" closed="2199"></route>
          <route destination1="MEX" destination2="MTY" opened="2009" closed="2199"></route>
          <route destination1="MEX" destination2="MXL" opened="2009" closed="2199"></route>
          <route destination1="MEX" destination2="MZT" opened="2009" closed="2199"></route>
          <route destination1="MEX" destination2="NLD" opened="2009" closed="2199"></route>
          <route destination1="MEX" destination2="OAX" opened="2009" closed="2199"></route>
          <route destination1="MEX" destination2="ORD" opened="2009" closed="2199"></route>
          <route destination1="MEX" destination2="PAZ" opened="2009" closed="2199"></route>
          <route destination1="MEX" destination2="PTY" opened="2009" closed="2199"></route>
          <route destination1="MEX" destination2="PVR" opened="2009" closed="2199"></route>
          <route destination1="MEX" destination2="REX" opened="2009" closed="2199"></route>
          <route destination1="MEX" destination2="SAL" opened="2009" closed="2199"></route>
          <route destination1="MEX" destination2="SAP" opened="2009" closed="2199"></route>
          <route destination1="MEX" destination2="SAT" opened="2009" closed="2199"></route>
          <route destination1="MEX" destination2="SCL" opened="2009" closed="2199"></route>
          <route destination1="MEX" destination2="SFO" opened="2009" closed="2199"></route>
          <route destination1="MEX" destination2="SJD" opened="2009" closed="2199"></route>
          <route destination1="MEX" destination2="SJO" opened="2009" closed="2199"></route>
          <route destination1="MEX" destination2="SLP" opened="2009" closed="2199"></route>
          <route destination1="MEX" destination2="SLW" opened="2009" closed="2199"></route>
          <route destination1="MEX" destination2="TAM" opened="2009" closed="2199"></route>
          <route destination1="MEX" destination2="TAP" opened="2009" closed="2199"></route>
          <route destination1="MEX" destination2="TGZ" opened="2009" closed="2199"></route>
          <route destination1="MEX" destination2="TIJ" opened="2009" closed="2199"></route>
          <route destination1="MEX" destination2="TRC" opened="2009" closed="2199"></route>
          <route destination1="MEX" destination2="VER" opened="2009" closed="2199"></route>
          <route destination1="MEX" destination2="VSA" opened="2009" closed="2199"></route>
          <route destination1="MEX" destination2="YUL" opened="2009" closed="2199"></route>
          <route destination1="MEX" destination2="ZCL" opened="2009" closed="2199"></route>
          <route destination1="MEX" destination2="ZIH" opened="2009" closed="2199"></route>
          <route destination1="MEX" destination2="ZLO" opened="2009" closed="2199"></route>
          <route destination1="MIA" destination2="MEX" opened="2009" closed="2199"></route>
          <route destination1="MIA" destination2="MID" opened="2009" closed="2199"></route>
          <route destination1="MID" destination2="MEX" opened="2009" closed="2199"></route>
          <route destination1="MID" destination2="MIA" opened="2009" closed="2199"></route>
          <route destination1="MID" destination2="VSA" opened="2009" closed="2199"></route>
          <route destination1="MLM" destination2="MEX" opened="2009" closed="2199"></route>
          <route destination1="MTT" destination2="MEX" opened="2009" closed="2199"></route>
          <route destination1="MTY" destination2="ATL" opened="2009" closed="2199"></route>
          <route destination1="MTY" destination2="BJX" opened="2009" closed="2199"></route>
          <route destination1="MTY" destination2="CJS" opened="2009" closed="2199"></route>
          <route destination1="MTY" destination2="CUL" opened="2009" closed="2199"></route>
          <route destination1="MTY" destination2="CUN" opened="2009" closed="2199"></route>
          <route destination1="MTY" destination2="CUU" opened="2009" closed="2199"></route>
          <route destination1="MTY" destination2="DTW" opened="2009" closed="2199"></route>
          <route destination1="MTY" destination2="GDL" opened="2009" closed="2199"></route>
          <route destination1="MTY" destination2="HMO" opened="2009" closed="2199"></route>
          <route destination1="MTY" destination2="LAS" opened="2009" closed="2199"></route>
          <route destination1="MTY" destination2="LRD" opened="2009" closed="2199"></route>
          <route destination1="MTY" destination2="MEX" opened="2009" closed="2199"></route>
          <route destination1="MTY" destination2="PBC" opened="2009" closed="2199"></route>
          <route destination1="MTY" destination2="PTY" opened="2009" closed="2199"></route>
          <route destination1="MTY" destination2="QRO" opened="2009" closed="2199"></route>
          <route destination1="MTY" destination2="SAT" opened="2009" closed="2199"></route>
          <route destination1="MTY" destination2="TAM" opened="2009" closed="2199"></route>
          <route destination1="MTY" destination2="TLC" opened="2009" closed="2199"></route>
          <route destination1="MTY" destination2="VER" opened="2009" closed="2199"></route>
          <route destination1="MXL" destination2="HMO" opened="2009" closed="2199"></route>
          <route destination1="MXL" destination2="MEX" opened="2009" closed="2199"></route>
          <route destination1="MZT" destination2="GDL" opened="2009" closed="2199"></route>
          <route destination1="MZT" destination2="LAX" opened="2009" closed="2199"></route>
          <route destination1="MZT" destination2="LMM" opened="2009" closed="2199"></route>
          <route destination1="MZT" destination2="MEX" opened="2009" closed="2199"></route>
          <route destination1="NLD" destination2="MEX" opened="2009" closed="2199"></route>
          <route destination1="NRT" destination2="MEX" opened="2009" closed="2199"></route>
          <route destination1="OAX" destination2="MEX" opened="2009" closed="2199"></route>
          <route destination1="ONT" destination2="GDL" opened="2009" closed="2199"></route>
          <route destination1="ORD" destination2="GDL" opened="2009" closed="2199"></route>
          <route destination1="ORD" destination2="MEX" opened="2009" closed="2199"></route>
          <route destination1="PAZ" destination2="MEX" opened="2009" closed="2199"></route>
          <route destination1="PBC" destination2="MTY" opened="2009" closed="2199"></route>
          <route destination1="PHX" destination2="HMO" opened="2009" closed="2199"></route>
          <route destination1="PMC" destination2="SCL" opened="2009" closed="2199"></route>
          <route destination1="PPE" destination2="HMO" opened="2009" closed="2199"></route>
          <route destination1="PPE" destination2="LAS" opened="2009" closed="2199"></route>
          <route destination1="PTY" destination2="CUN" opened="2009" closed="2199"></route>
          <route destination1="PTY" destination2="GDL" opened="2009" closed="2199"></route>
          <route destination1="PTY" destination2="MEX" opened="2009" closed="2199"></route>
          <route destination1="PTY" destination2="MTY" opened="2009" closed="2199"></route>
          <route destination1="PUQ" destination2="PMC" opened="2009" closed="2199"></route>
          <route destination1="PVG" destination2="TIJ" opened="2009" closed="2199"></route>
          <route destination1="PVR" destination2="ATL" opened="2009" closed="2199"></route>
          <route destination1="PVR" destination2="GDL" opened="2009" closed="2199"></route>
          <route destination1="PVR" destination2="LAX" opened="2009" closed="2199"></route>
          <route destination1="PVR" destination2="MEX" opened="2009" closed="2199"></route>
          <route destination1="PVR" destination2="SAN" opened="2009" closed="2199"></route>
          <route destination1="PVR" destination2="SFO" opened="2009" closed="2199"></route>
          <route destination1="QRO" destination2="MTY" opened="2009" closed="2199"></route>
          <route destination1="REX" destination2="MEX" opened="2009" closed="2199"></route>
          <route destination1="SAL" destination2="MEX" opened="2009" closed="2199"></route>
          <route destination1="SAN" destination2="PVR" opened="2009" closed="2199"></route>
          <route destination1="SAP" destination2="MEX" opened="2009" closed="2199"></route>
          <route destination1="SAT" destination2="MEX" opened="2009" closed="2199"></route>
          <route destination1="SAT" destination2="MTY" opened="2009" closed="2199"></route>
          <route destination1="SCL" destination2="MEX" opened="2009" closed="2199"></route>
          <route destination1="SFO" destination2="MEX" opened="2009" closed="2199"></route>
          <route destination1="SFO" destination2="PVR" opened="2009" closed="2199"></route>
          <route destination1="SFO" destination2="SJD" opened="2009" closed="2199"></route>
          <route destination1="SJC" destination2="GDL" opened="2009" closed="2199"></route>
          <route destination1="SJC" destination2="SJD" opened="2009" closed="2199"></route>
          <route destination1="SJD" destination2="ATL" opened="2009" closed="2199"></route>
          <route destination1="SJD" destination2="LAX" opened="2009" closed="2199"></route>
          <route destination1="SJD" destination2="MEX" opened="2009" closed="2199"></route>
          <route destination1="SJD" destination2="SFO" opened="2009" closed="2199"></route>
          <route destination1="SJD" destination2="SJC" opened="2009" closed="2199"></route>
          <route destination1="SJO" destination2="MEX" opened="2009" closed="2199"></route>
          <route destination1="SLC" destination2="CUN" opened="2009" closed="2199"></route>
          <route destination1="SLC" destination2="GDL" opened="2009" closed="2199"></route>
          <route destination1="SLP" destination2="MEX" opened="2009" closed="2199"></route>
          <route destination1="SLW" destination2="MEX" opened="2009" closed="2199"></route>
          <route destination1="SMF" destination2="GDL" opened="2009" closed="2199"></route>
          <route destination1="TAM" destination2="MEX" opened="2009" closed="2199"></route>
          <route destination1="TAM" destination2="MTY" opened="2009" closed="2199"></route>
          <route destination1="TAM" destination2="VER" opened="2009" closed="2199"></route>
          <route destination1="TAP" destination2="MEX" opened="2009" closed="2199"></route>
          <route destination1="TGZ" destination2="MEX" opened="2009" closed="2199"></route>
          <route destination1="TIJ" destination2="BJX" opened="2009" closed="2199"></route>
          <route destination1="TIJ" destination2="CJS" opened="2009" closed="2199"></route>
          <route destination1="TIJ" destination2="DGO" opened="2009" closed="2199"></route>
          <route destination1="TIJ" destination2="HMO" opened="2009" closed="2199"></route>
          <route destination1="TIJ" destination2="MEX" opened="2009" closed="2199"></route>
          <route destination1="TIJ" destination2="NRT" opened="2009" closed="2199"></route>
          <route destination1="TIJ" destination2="PVG" opened="2009" closed="2199"></route>
          <route destination1="TLC" destination2="ACA" opened="2009" closed="2199"></route>
          <route destination1="TLC" destination2="CUN" opened="2009" closed="2199"></route>
          <route destination1="TLC" destination2="GDL" opened="2009" closed="2199"></route>
          <route destination1="TLC" destination2="MTY" opened="2009" closed="2199"></route>
          <route destination1="TPA" destination2="CUN" opened="2009" closed="2199"></route>
          <route destination1="TRC" destination2="CUU" opened="2009" closed="2199"></route>
          <route destination1="TRC" destination2="GDL" opened="2009" closed="2199"></route>
          <route destination1="TRC" destination2="MEX" opened="2009" closed="2199"></route>
          <route destination1="VER" destination2="MEX" opened="2009" closed="2199"></route>
          <route destination1="VER" destination2="MTY" opened="2009" closed="2199"></route>
          <route destination1="VER" destination2="TAM" opened="2009" closed="2199"></route>
          <route destination1="VER" destination2="VSA" opened="2009" closed="2199"></route>
          <route destination1="VSA" destination2="MEX" opened="2009" closed="2199"></route>
          <route destination1="VSA" destination2="MID" opened="2009" closed="2199"></route>
          <route destination1="VSA" destination2="VER" opened="2009" closed="2199"></route>
          <route destination1="YUL" destination2="MEX" opened="2009" closed="2199"></route>
          <route destination1="ZCL" destination2="MEX" opened="2009" closed="2199"></route>
          <route destination1="ZIH" destination2="LAX" opened="2009" closed="2199"></route>
          <route destination1="ZIH" destination2="MEX" opened="2009" closed="2199"></route>
          <route destination1="ZLO" destination2="LAX" opened="2009" closed="2199"></route>
          <route destination1="ZLO" destination2="MEX" opened="2009" closed="2199"></route>
          </routes>
  <!--the airliners the airline would start with which isn't on a route earyl (1960) late (2010)-->
  <airliners>
    <airliner type="Boeing 737-700" early="0" late="30"></airliner>  
    <airliner type="Boeing 737-800" early="0" late="15"></airliner>
    <airliner type="Boeing 767-300ER" early="0" late="7"></airliner>
    <airliner type="Boeing 777-200ER" early="0" late="4"></airliner>
    <airliner type="Boeing 767-200ER" early="0" late="2"></airliner>
    <airliner type="Boeing 787-8" early="0" late="3"></airliner>
  </airliners>
  </startdata>
</airline>
